mannapass.py
mannapass-1.dist-info/METADATA
mannapass-1.dist-info/WHEEL
mannapass-1.dist-info/top_level.txt
mannapass-1.dist-info/RECORD
