Metadata-Version: 2.1
Name: mannapass
Version: 1
Summary: long distance file reciever
Author: Neelanjan Manna
Classifier: Programming Language :: Python :: 3
Classifier: License :: OSI Approved :: MIT License
Classifier: Operating System :: OS Independent
Requires-Python: >=3.6
Requires-Dist: easygui
